quantscape/__init__.py
quantscape/data.py
quantscape/models.py
quantscape/utils.py
tests/__init__.py
tests/test_models.py
quantscape-0.1.0.dist-info/LICENSE
quantscape-0.1.0.dist-info/METADATA
quantscape-0.1.0.dist-info/WHEEL
quantscape-0.1.0.dist-info/top_level.txt
quantscape-0.1.0.dist-info/RECORD
