Metadata-Version: 2.1
Name: quantscape
Version: 0.1.0
Summary: A quantitative finance Python library for option pricing, volatility insights & Greeks computation.
Home-page: https://github.com/cam-schmidt/quantscape.git
Author: Cam Schmidt
License: MIT License
License-File: LICENSE
Requires-Dist: numpy
Requires-Dist: scipy
